README.md
prettyparse.py
setup.py
prettyparse.egg-info/PKG-INFO
prettyparse.egg-info/SOURCES.txt
prettyparse.egg-info/dependency_links.txt
prettyparse.egg-info/top_level.txt
prettyparse.egg-info/zip-safe
test/test_parser.py