Metadata-Version: 1.1
Name: prettyparse
Version: 1.0.0
Summary: A clean, simple way to create Python argument parsers
Home-page: https://github.com/MatthewScholefield/prettyparse
Author: Matthew Scholefield
Author-email: matthew331199@gmail.com
License: UNKNOWN
Keywords: argumentparser argparse argument parser command line
Platform: UNKNOWN
Classifier: Development Status :: 3 - Alpha
Classifier: Intended Audience :: Developers
Classifier: License :: OSI Approved :: MIT License
Classifier: Topic :: Software Development :: Libraries :: Python Modules
Classifier: Programming Language :: Python :: 2
Classifier: Programming Language :: Python :: 2.7
Classifier: Programming Language :: Python :: 3
Classifier: Programming Language :: Python :: 3.0
Classifier: Programming Language :: Python :: 3.1
Classifier: Programming Language :: Python :: 3.2
Classifier: Programming Language :: Python :: 3.3
Classifier: Programming Language :: Python :: 3.4
Classifier: Programming Language :: Python :: 3.5
Classifier: Programming Language :: Python :: 3.6
